pythonbible_bbe/__init__.py
pythonbible_bbe/html_bible.py
pythonbible_bbe/html_notes_bible.py
pythonbible_bbe/html_readers_bible.py
pythonbible_bbe/plain_text_bible.py
pythonbible_bbe/plain_text_notes_bible.py
pythonbible_bbe/plain_text_readers_bible.py
pythonbible_bbe-0.0.1.dist-info/WHEEL
pythonbible_bbe-0.0.1.dist-info/METADATA
pythonbible_bbe-0.0.1.dist-info/RECORD
