Metadata-Version: 2.4
Name: pythonbible-bbe
Version: 0.0.1
Author: Nathan Patton
Author-email: Nathan Patton <npatton@gmail.com>
License-Expression: MIT
Classifier: Intended Audience :: Information Technology
Classifier: Intended Audience :: Developers
Classifier: Operating System :: OS Independent
Classifier: Topic :: Software Development :: Libraries :: Python Modules
Classifier: Topic :: Software Development :: Libraries
Classifier: Topic :: Software Development
Classifier: Programming Language :: Python
Classifier: Programming Language :: Python :: 3
Classifier: Programming Language :: Python :: 3 :: Only
Classifier: Programming Language :: Python :: 3.10
Classifier: Programming Language :: Python :: 3.11
Classifier: Programming Language :: Python :: 3.12
Classifier: Programming Language :: Python :: 3.13
Classifier: Programming Language :: Python :: 3.14
Classifier: License :: OSI Approved :: MIT License
Requires-Dist: pythonbible
Requires-Python: >=3.10
Project-URL: Documentation, https://docs.python.bible
Project-URL: Source, https://github.com/avendesora/pythonbible
